{
  "track": "silverstone 2019 gp",
  "sessions": 56,
  "laps": 184,
  "resets": 283,
  "resetHotspotsBins": [
    {
      "startPct": 0.0,
      "endPct": 0.05,
      "count": 29
    },
    {
      "startPct": 0.05,
      "endPct": 0.1,
      "count": 5
    },
    {
      "startPct": 0.1,
      "endPct": 0.15,
      "count": 2
    },
    {
      "startPct": 0.15,
      "endPct": 0.2,
      "count": 15
    },
    {
      "startPct": 0.2,
      "endPct": 0.25,
      "count": 6
    },
    {
      "startPct": 0.25,
      "endPct": 0.3,
      "count": 1
    },
    {
      "startPct": 0.35,
      "endPct": 0.4,
      "count": 2
    },
    {
      "startPct": 0.55,
      "endPct": 0.6,
      "count": 2
    },
    {
      "startPct": 0.65,
      "endPct": 0.7,
      "count": 2
    },
    {
      "startPct": 0.7,
      "endPct": 0.75,
      "count": 1
    },
    {
      "startPct": 0.9,
      "endPct": 0.95,
      "count": 1
    },
    {
      "startPct": 0.95,
      "endPct": 1.0,
      "count": 217
    }
  ],
  "durationHours": 14.06
}